photoshopapi/__init__.py
photoshopapi/__init__.pyi
photoshopapi/_group_layer.pyi
photoshopapi/_image_layer.pyi
photoshopapi/_layer.pyi
photoshopapi/_layered_file.pyi
photoshopapi/_photoshop_file.pyi
photoshopapi/_smart_object_layer.pyi
photoshopapi/_smart_object_warp.pyi
photoshopapi/py.typed
photoshopapi/enum/__init__.py
photoshopapi/enum/__init__.pyi
photoshopapi/enum/_bit_depth.pyi
photoshopapi/enum/_blend_mode.pyi
photoshopapi/enum/_channel_id.pyi
photoshopapi/enum/_color_mode.pyi
photoshopapi/enum/_compression.pyi
photoshopapi/enum/_linked_layer_type.pyi
photoshopapi/geometry/__init__.py
photoshopapi/geometry/__init__.pyi
photoshopapi/geometry/_operations.pyi
photoshopapi/geometry/_point2d.pyi
photoshopapi/include/simdutf.h
photoshopapi/include/mio/mmap.hpp
photoshopapi/include/mio/page.hpp
photoshopapi/include/mio/shared_mmap.hpp
photoshopapi/include/mio/detail/mmap.ipp
photoshopapi/include/mio/detail/string_util.hpp
photoshopapi/include/simdutf/avx512.h
photoshopapi/include/simdutf/common_defs.h
photoshopapi/include/simdutf/compiler_check.h
photoshopapi/include/simdutf/encoding_types.h
photoshopapi/include/simdutf/error.h
photoshopapi/include/simdutf/implementation.h
photoshopapi/include/simdutf/portability.h
photoshopapi/include/simdutf/simdutf_version.h
photoshopapi/include/simdutf/internal/isadetection.h
photoshopapi/lib64/libsimdutf.a
photoshopapi/lib64/photoshopapi.cpython-311-x86_64-linux-gnu.so
photoshopapi/lib64/cmake/simdutf/simdutf-config-version.cmake
photoshopapi/lib64/cmake/simdutf/simdutf-config.cmake
photoshopapi/lib64/cmake/simdutf/simdutfTargets-release.cmake
photoshopapi/lib64/cmake/simdutf/simdutfTargets.cmake
photoshopapi/lib64/pkgconfig/simdutf.pc
photoshopapi/share/cmake/mio/mio-config-version.cmake
photoshopapi/share/cmake/mio/mio-config.cmake
photoshopapi/share/cmake/mio/mio-targets.cmake
photoshopapi/util/__init__.py
photoshopapi/util/__init__.pyi
photoshopapi-0.8.0.dist-info/METADATA
photoshopapi-0.8.0.dist-info/WHEEL
photoshopapi-0.8.0.dist-info/RECORD
photoshopapi-0.8.0.dist-info/licenses/LICENSE
