Metadata-Version: 2.2
Name: PhotoshopAPI
Version: 0.8.0
Summary: A performant read/write parser of Photoshop Files (*.psd and *.psb)
Author-Email: Emil Dohne <emildohne@gmail.com>
Maintainer-Email: Emil Dohne <emildohne@gmail.com>
License: BSD-3-Clause
Classifier: Natural Language :: English
Classifier: Operating System :: OS Independent
Classifier: Programming Language :: Python :: 3
Classifier: Programming Language :: Python :: 3.8
Classifier: Programming Language :: Python :: 3.9
Classifier: Programming Language :: Python :: 3.10
Classifier: Programming Language :: Python :: 3.11
Classifier: Programming Language :: Python :: 3.12
Classifier: Programming Language :: Python :: 3.13
Classifier: Topic :: Software Development :: Libraries :: Python Modules
Project-URL: Homepage, https://photoshopapi.readthedocs.org/
Project-URL: Source, https://github.com/EmilDohne/PhotoshopAPI
Project-URL: Documentation, https://photoshopapi.readthedocs.org/
Project-URL: Issues, https://github.com/EmilDohne/PhotoshopAPI/issues
Requires-Python: >=3.8
Requires-Dist: numpy>=1.21.6
